pnc_cli/__init__.py
pnc_cli/archives.py
pnc_cli/bpmbuildconfigurations.py
pnc_cli/brewpush.py
pnc_cli/buildconfigsetrecords.py
pnc_cli/buildconfigurations.py
pnc_cli/buildconfigurationsets.py
pnc_cli/buildrecords.py
pnc_cli/builds.py
pnc_cli/cli_types.py
pnc_cli/common.py
pnc_cli/environments.py
pnc_cli/generate_repo.py
pnc_cli/genericsetting.py
pnc_cli/keycloak_config.py
pnc_cli/licenses.py
pnc_cli/makemead.py
pnc_cli/pnc.py
pnc_cli/pnc_api.py
pnc_cli/pnc_help_formatter.py
pnc_cli/pnc_server_config.py
pnc_cli/productmilestones.py
pnc_cli/productreleases.py
pnc_cli/products.py
pnc_cli/productversions.py
pnc_cli/projects.py
pnc_cli/repositoryconfigurations.py
pnc_cli/runningbuilds.py
pnc_cli/user_config.py
pnc_cli/users.py
pnc_cli/utils.py
pnc_cli/swagger_client/__init__.py
pnc_cli/swagger_client/api_client.py
pnc_cli/swagger_client/configuration.py
pnc_cli/swagger_client/rest.py
pnc_cli/swagger_client/apis/__init__.py
pnc_cli/swagger_client/apis/artifacts_api.py
pnc_cli/swagger_client/apis/bpm_api.py
pnc_cli/swagger_client/apis/buildconfigsetrecords_api.py
pnc_cli/swagger_client/apis/buildconfigurations_api.py
pnc_cli/swagger_client/apis/buildconfigurationsets_api.py
pnc_cli/swagger_client/apis/buildrecordpush_api.py
pnc_cli/swagger_client/apis/buildrecords_api.py
pnc_cli/swagger_client/apis/builds_api.py
pnc_cli/swagger_client/apis/buildtasks_api.py
pnc_cli/swagger_client/apis/environments_api.py
pnc_cli/swagger_client/apis/genericsetting_api.py
pnc_cli/swagger_client/apis/licenses_api.py
pnc_cli/swagger_client/apis/productmilestones_api.py
pnc_cli/swagger_client/apis/productreleases_api.py
pnc_cli/swagger_client/apis/products_api.py
pnc_cli/swagger_client/apis/productversions_api.py
pnc_cli/swagger_client/apis/projects_api.py
pnc_cli/swagger_client/apis/repositoryconfigurations_api.py
pnc_cli/swagger_client/apis/runningbuildrecords_api.py
pnc_cli/swagger_client/apis/test_api.py
pnc_cli-1.8.0.dist-info/DESCRIPTION.rst
pnc_cli-1.8.0.dist-info/METADATA
pnc_cli-1.8.0.dist-info/RECORD
pnc_cli-1.8.0.dist-info/WHEEL
pnc_cli-1.8.0.dist-info/entry_points.txt
pnc_cli-1.8.0.dist-info/metadata.json
pnc_cli-1.8.0.dist-info/top_level.txt
